tests
mongorm
