Metadata-Version: 1.1
Name: mongorm
Version: 0.6.7
Summary: An extremely thin ORM-ish wrapper over pymongo.
Home-page: https://github.com/rahulg/mongorm
Author: Rahul AG
Author-email: r@hul.ag
License: BSD
Keywords: mongodb,mongo,orm,odm
Platform: UNKNOWN
Classifier: Development Status :: 3 - Alpha
Classifier: Topic :: Database :: Front-Ends
Classifier: License :: OSI Approved :: BSD License
Classifier: Intended Audience :: Developers
Classifier: Operating System :: OS Independent
